tobj/__init__.py
tobj/errors.py
tobj/interpreter.py
tobj/lexer.py
tobj/main.py
tobj/parser.py
tobj-0.2.3.dist-info/licenses/LICENSE
tobj-0.2.3.dist-info/METADATA
tobj-0.2.3.dist-info/WHEEL
tobj-0.2.3.dist-info/top_level.txt
tobj-0.2.3.dist-info/RECORD
