Metadata-Version: 2.4
Name: tobj
Version: 0.2.3
Summary: A cool, tiny, minimal data format
Author-email: Razka Rizaldi <razka.rizaldis@gmail.com>, tyydev1 <torchist@proton.me>
License-Expression: MIT
Project-URL: Homepage, https://github.com/tyydev1/tinyobj
Project-URL: Repository, https://github.com/tyydev1/tinyobj
Project-URL: Issues, https://github.com/tyydev1/tinyobj/issues
Keywords: library,language,data,format,programming
Classifier: Development Status :: 4 - Beta
Classifier: Intended Audience :: Developers
Classifier: Programming Language :: Python :: 3
Classifier: Programming Language :: Python :: 3.8
Classifier: Programming Language :: Python :: 3.9
Classifier: Programming Language :: Python :: 3.10
Classifier: Programming Language :: Python :: 3.11
Classifier: Programming Language :: Python :: 3.12
Requires-Python: >=3.8
License-File: LICENSE
Provides-Extra: dev
Requires-Dist: pytest>=7.0.0; extra == "dev"
Requires-Dist: black>=23.0.0; extra == "dev"
Requires-Dist: mypy>=1.0.0; extra == "dev"
Requires-Dist: tinycolors>=0.6.0; extra == "dev"
Requires-Dist: sphinx>=5.0.0; extra == "dev"
Requires-Dist: sphinx-autoapi>=3.5.0; extra == "dev"
Requires-Dist: furo>=2024.8.6; extra == "dev"
Dynamic: license-file
